gradio_xyslider/__init__.py
gradio_xyslider/automationbus.pyi
gradio_xyslider/xyslider.py
gradio_xyslider/xyslider.pyi
gradio_xyslider/xysliderbus.pyi
gradio_xyslider/templates/component/Index-DmbbsQLU.js
gradio_xyslider/templates/component/_basePickBy-DJrxYAP1.js
gradio_xyslider/templates/component/_baseUniq-1UdPJf29.js
gradio_xyslider/templates/component/arc-jVPZ9C3O.js
gradio_xyslider/templates/component/architectureDiagram-VXUJARFQ-DzdG29VX.js
gradio_xyslider/templates/component/auto-render-16_rLRwR.js
gradio_xyslider/templates/component/blockDiagram-VD42YOAC-CCRKi9XO.js
gradio_xyslider/templates/component/c4Diagram-YG6GDRKO-BADYC-Yc.js
gradio_xyslider/templates/component/channel-BhyCVuox.js
gradio_xyslider/templates/component/chunk-4BX2VUAB-DWM31aYp.js
gradio_xyslider/templates/component/chunk-55IACEB6-FOY9cuAX.js
gradio_xyslider/templates/component/chunk-B4BG7PRW-6QSMBB9P.js
gradio_xyslider/templates/component/chunk-DI55MBZ5-BMSeB6c7.js
gradio_xyslider/templates/component/chunk-FMBD7UC4-DtolC5I0.js
gradio_xyslider/templates/component/chunk-QN33PNHL-Bfaw2T0f.js
gradio_xyslider/templates/component/chunk-QZHKN3VN-C3wUbUvH.js
gradio_xyslider/templates/component/chunk-TZMSLE5B-D6pZIK0R.js
gradio_xyslider/templates/component/classDiagram-2ON5EDUG-HbCSAc5o.js
gradio_xyslider/templates/component/classDiagram-v2-WZHVMYZB-HbCSAc5o.js
gradio_xyslider/templates/component/clone-CZQLzGSG.js
gradio_xyslider/templates/component/cose-bilkent-S5V4N54A-Df8qbP7F.js
gradio_xyslider/templates/component/cytoscape.esm-ZmItrg9y.js
gradio_xyslider/templates/component/dagre-6UL2VRFP-UQl1ma97.js
gradio_xyslider/templates/component/defaultLocale-D7EN2tov.js
gradio_xyslider/templates/component/diagram-PSM6KHXK-Dl5oZNai.js
gradio_xyslider/templates/component/diagram-QEK2KX5R-B2lo9Epb.js
gradio_xyslider/templates/component/diagram-S2PKOQOG-Bgcu95gp.js
gradio_xyslider/templates/component/erDiagram-Q2GNP2WA-oQMF66e6.js
gradio_xyslider/templates/component/flowDiagram-NV44I4VS-MxFWZKZO.js
gradio_xyslider-0.0.2.dist-info/METADATA
gradio_xyslider-0.0.2.dist-info/WHEEL
gradio_xyslider-0.0.2.dist-info/RECORD
